README.md
setup.cfg
setup.py
fabulus/__init__.py
fabulus/labels.py
fabulus/util.py
fabulus.egg-info/PKG-INFO
fabulus.egg-info/SOURCES.txt
fabulus.egg-info/dependency_links.txt
fabulus.egg-info/requires.txt
fabulus.egg-info/top_level.txt
fabulus/_internal/__init__.py
fabulus/_internal/utils.py
fabulus/io/__init__.py
fabulus/io/serial.py
fabulus/net/__init__.py
fabulus/net/tf.py
fabulus/postprocessing/__init__.py
fabulus/postprocessing/window.py
fabulus/unsup/__init__.py
fabulus/unsup/spca.py
fabulus/vis/__init__.py
fabulus/vis/downproject.py
fabulus/vis/frequencies.py
fabulus/vis/matrix.py
fabulus/vis/scree.py