Metadata-Version: 1.1
Name: fabulus
Version: 0.3rc0
Summary: Utility packages for Machine Learning and Data Visualisation
Home-page: https://github.com/AlexRaschl/FABULUS-A-machine-learning-enterprise
Author: Stefan B, Alexander R
Author-email: Steve2608@users.noreply.github.com
License: UNKNOWN
Download-URL: https://github.com/AlexRaschl/FABULUS-A-machine-learning-enterprise/archive/v_0.3rc0.tar.gz
Platform: UNKNOWN
Classifier: Programming Language :: Python :: 3.6
Classifier: Operating System :: OS Independent
